README.md
setup.py
baraat/__init__.py
baraat/language_router.py
baraat/utilities.py
baraat.egg-info/PKG-INFO
baraat.egg-info/SOURCES.txt
baraat.egg-info/dependency_links.txt
baraat.egg-info/requires.txt
baraat.egg-info/top_level.txt