Metadata-Version: 2.1
Name: baraat
Version: 1.1.6
Summary: Project Baarat enhances accessibility to India's linguistic diversity through technology. It's an open-source initiative using LLMs for Indic-NLP tasks. Features include tokenizers for Indian languages and fine-tuned LLMs for accurate text generation. It fosters community-driven innovation and offers high-quality datasets for training. NOTE: The Kannada experts model is under development and is not meant to be used as of now. A future release will enable the model to be used for inferen
Author: Project Baraat
Author-email: akash.kamalesh03@gmail.com
Classifier: Programming Language :: Python :: 3
Classifier: License :: OSI Approved :: MIT License
Classifier: Operating System :: OS Independent
Requires-Python: >=3.9
